[
  {
    "id": "1",
    "userName": "Monica",
    "email": "monica@gmail.com",
    "password": "1234",
    "houseName": "Oportos",
    "color": "coral"
  },
  {
    "id": "2",
    "userName": "Manuel",
    "email": "manuel@gmail.com",
    "password": "9876",
    "houseName": "Oportos",
    "color": "green"
  },
  {
    "id": "3",
    "userName": "Tete",
    "email": "tete@gmail.com",
    "password": "1234",
    "houseName": "Coyoacan",
    "color": "lilac"
  },
  {
    "id": "4",
    "userName": "Guante",
    "email": "guante@gmail.com",
    "password": "9876",
    "houseName": "Coyoacan",
    "color": "yellow"
  },
  {
    "id": "5",
    "userName": "Petite",
    "email": "petite@gmail.com",
    "password": "2468",
    "houseName": "Coyoacan",
    "color": "green"
  },
  {
    "id": "5ccafa40-e757-4caf-a9b5-0ddb8c1c2ff1",
    "userName": "Memin",
    "password": "1234",
    "houseName": "Oportos",
    "color": "lilac"
  }
]
